Workbook

Sheet README
A1: ACCIGEN — Project Portfolio Command Assistant | Prototype v1
A3: Purpose | B3: Create a synthetic project portfolio that lets a Project Financial Analyst or Business Analyst test command-based questions without navigating project-by-project.
A4: Core concept | B4: ERP/System data → portfolio data layer → AI interpretation → priority → recommended action
A5: Primary personas | B5: Project Financial Analyst; Business Analyst
A6: Prototype scope | B6: 20 synthetic projects; 10 locked command questions; attention scoring across milestone, billing, revenue, time, acceptance and margin signals.
A7: Data policy | B7: All project data is synthetic and created for ACCIGEN. No Oracle, customer, or employer confidential information is used.
A9: Next build step | B9: Build the command logic / agent behavior that converts each natural-language question into a deterministic query and a concise answer.

Sheet Projects
A1: Project ID | B1: Project Name | C1: Customer | D1: Project Manager | E1: PFA Owner | F1: BA Owner | G1: Status | H1: Contract Value ($000) | I1: Budget Cost ($000) | J1: Actual Cost ($000) | K1: Forecast Cost ($000) | L1: Recognised Revenue ($000) | M1: Forecast Revenue ($000) | N1: Gross Margin % | O1: Forecast Margin % | P1: Milestone Name | Q1: Milestone Due Date | R1: Milestone Status | S1: Invoice Amount ($000) | T1: Invoice Due Date | U1: Invoice Status | V1: Revenue Event | W1: Expected Revenue Date | X1: Revenue Status | Y1: Planned Hours | Z1: Submitted Hours | AA1: Actual Hours | AB1: Customer Deliverable | AC1: Deliverable Submitted Date | AD1: Customer Acceptance Status | AE1: Acceptance Due Date | AF1: Last Review Date | AG1: Days to Milestone | AH1: Milestone Attention | AI1: Invoice Attention | AJ1: Revenue Attention | AK1: Time Attention | AL1: Acceptance Attention | AM1: Margin Attention | AN1: Overall Attention Score | AO1: Priority Band
A2: P-001 | B2: Orion Cloud Migration | C2: Apex Manufacturing | D2: R. Mehta | E2: PFA-01 | F2: BA-01 | G2: Active | H2: 1250 | I2: 820 | J2: 610 | K2: 890 | L2: 700 | M2: 1180 | N2: =IFERROR((L2-J2)/L2,0) | O2: =IFERROR((M2-K2)/M2,0) | P2: Design Sign-off | Q2: 46267 | R2: Missed | S2: 150 | T2: 46268 | U2: Due | V2: Phase 2 Revenue | W2: 46265 | X2: Pending | Y2: 320 | Z2: 300 | AA2: 360 | AB2: Design Package | AC2: 46258 | AD2: Pending | AE2: 46266 | AF2: 46262 | AG2: =Q2-Controls!$B$2 | AH2: =IF(R2="Missed",3,IF(AND(R2="Upcoming",AG2<=Controls!$B$3),2,0)) | AI2: =IF(U2="Overdue",3,IF(U2="Due",2,IF(U2="Due Soon",1,0))) | AJ2: =IF(X2="Missed",3,IF(X2="Ready",2,0)) | AK2: =IF(OR(AA2>25,AA2>Y2*(1+Controls!$B$5)),2,IF(Z2<Y2,2,0)) | AL2: =IF(AND(AD2="Pending",Controls!$B$2-AC2>Controls!$B$4),2,IF(AD2="Pending",1,0)) | AM2: =IF(O2<15%,2,IF(O2<Controls!$B$6,1,0)) | AN2: =SUM(AH2:AM2) | AO2: =IF(AN2>=Controls!$B$7,"High",IF(AN2>=Controls!$B$8,"Medium","Normal"))
A3: P-002 | B3: Atlas ERP Upgrade | C3: Northstar Retail | D3: S. Iyer | E3: PFA-01 | F3: BA-01 | G3: Active | H3: 980 | I3: 650 | J3: 470 | K3: 620 | L3: 520 | M3: 930 | N3: =IFERROR((L3-J3)/L3,0) | O3: =IFERROR((M3-K3)/M3,0) | P3: UAT Complete | Q3: 46275 | R3: Upcoming | S3: 100 | T3: 46283 | U3: Not Due | V3: UAT Revenue | W3: 46280 | X3: Pending | Y3: 180 | Z3: 180 | AA3: 175 | AB3: UAT Sign-off | AC3: 46264 | AD3: Accepted | AE3: 46270 | AF3: 46265 | AG3: =Q3-Controls!$B$2 | AH3: =IF(R3="Missed",3,IF(AND(R3="Upcoming",AG3<=Controls!$B$3),2,0)) | AI3: =IF(U3="Overdue",3,IF(U3="Due",2,IF(U3="Due Soon",1,0))) | AJ3: =IF(X3="Missed",3,IF(X3="Ready",2,0)) | AK3: =IF(OR(AA3>25,AA3>Y3*(1+Controls!$B$5)),2,IF(Z3<Y3,2,0)) | AL3: =IF(AND(AD3="Pending",Controls!$B$2-AC3>Controls!$B$4),2,IF(AD3="Pending",1,0)) | AM3: =IF(O3<15%,2,IF(O3<Controls!$B$6,1,0)) | AN3: =SUM(AH3:AM3) | AO3: =IF(AN3>=Controls!$B$7,"High",IF(AN3>=Controls!$B$8,"Medium","Normal"))
A4: P-003 | B4: Beacon Analytics | C4: Vertex Telecom | D4: A. Khan | E4: PFA-01 | F4: BA-02 | G4: Active | H4: 760 | I4: 510 | J4: 390 | K4: 525 | L4: 410 | M4: 720 | N4: =IFERROR((L4-J4)/L4,0) | O4: =IFERROR((M4-K4)/M4,0) | P4: Customer Acceptance | Q4: 46269 | R4: Upcoming | S4: 90 | T4: 46272 | U4: Due Soon | V4: Final Revenue | W4: 46271 | X4: Ready | Y4: 140 | Z4: 140 | AA4: 138 | AB4: Analytics Release | AC4: 46263 | AD4: Pending | AE4: 46268 | AF4: 46263 | AG4: =Q4-Controls!$B$2 | AH4: =IF(R4="Missed",3,IF(AND(R4="Upcoming",AG4<=Controls!$B$3),2,0)) | AI4: =IF(U4="Overdue",3,IF(U4="Due",2,IF(U4="Due Soon",1,0))) | AJ4: =IF(X4="Missed",3,IF(X4="Ready",2,0)) | AK4: =IF(OR(AA4>25,AA4>Y4*(1+Controls!$B$5)),2,IF(Z4<Y4,2,0)) | AL4: =IF(AND(AD4="Pending",Controls!$B$2-AC4>Controls!$B$4),2,IF(AD4="Pending",1,0)) | AM4: =IF(O4<15%,2,IF(O4<Controls!$B$6,1,0)) | AN4: =SUM(AH4:AM4) | AO4: =IF(AN4>=Controls!$B$7,"High",IF(AN4>=Controls!$B$8,"Medium","Normal"))
A5: P-004 | B5: Cedar Data Platform | C5: BluePeak Energy | D5: M. Rao | E5: PFA-02 | F5: BA-02 | G5: Active | H5: 1500 | I5: 1000 | J5: 790 | K5: 1120 | L5: 880 | M5: 1410 | N5: =IFERROR((L5-J5)/L5,0) | O5: =IFERROR((M5-K5)/M5,0) | P5: Go-Live | Q5: 46280 | R5: Upcoming | S5: 220 | T5: 46281 | U5: Not Due | V5: Go-Live Revenue | W5: 46280 | X5: Pending | Y5: 460 | Z5: 410 | AA5: 505 | AB5: Go-Live Acceptance | AC5: 46266 | AD5: Pending | AE5: 46283 | AF5: 46264 | AG5: =Q5-Controls!$B$2 | AH5: =IF(R5="Missed",3,IF(AND(R5="Upcoming",AG5<=Controls!$B$3),2,0)) | AI5: =IF(U5="Overdue",3,IF(U5="Due",2,IF(U5="Due Soon",1,0))) | AJ5: =IF(X5="Missed",3,IF(X5="Ready",2,0)) | AK5: =IF(OR(AA5>25,AA5>Y5*(1+Controls!$B$5)),2,IF(Z5<Y5,2,0)) | AL5: =IF(AND(AD5="Pending",Controls!$B$2-AC5>Controls!$B$4),2,IF(AD5="Pending",1,0)) | AM5: =IF(O5<15%,2,IF(O5<Controls!$B$6,1,0)) | AN5: =SUM(AH5:AM5) | AO5: =IF(AN5>=Controls!$B$7,"High",IF(AN5>=Controls!$B$8,"Medium","Normal"))
A6: P-005 | B6: Delta Automation | C6: Summit Logistics | D6: N. Sen | E6: PFA-02 | F6: BA-03 | G6: Active | H6: 430 | I6: 300 | J6: 245 | K6: 335 | L6: 280 | M6: 405 | N6: =IFERROR((L6-J6)/L6,0) | O6: =IFERROR((M6-K6)/M6,0) | P6: Automation Pilot | Q6: 46277 | R6: Upcoming | S6: 65 | T6: 46277 | U6: Due Soon | V6: Pilot Revenue | W6: 46277 | X6: Ready | Y6: 120 | Z6: 112 | AA6: 131 | AB6: Pilot Results | AC6: 46261 | AD6: Pending | AE6: 46271 | AF6: 46261 | AG6: =Q6-Controls!$B$2 | AH6: =IF(R6="Missed",3,IF(AND(R6="Upcoming",AG6<=Controls!$B$3),2,0)) | AI6: =IF(U6="Overdue",3,IF(U6="Due",2,IF(U6="Due Soon",1,0))) | AJ6: =IF(X6="Missed",3,IF(X6="Ready",2,0)) | AK6: =IF(OR(AA6>25,AA6>Y6*(1+Controls!$B$5)),2,IF(Z6<Y6,2,0)) | AL6: =IF(AND(AD6="Pending",Controls!$B$2-AC6>Controls!$B$4),2,IF(AD6="Pending",1,0)) | AM6: =IF(O6<15%,2,IF(O6<Controls!$B$6,1,0)) | AN6: =SUM(AH6:AM6) | AO6: =IF(AN6>=Controls!$B$7,"High",IF(AN6>=Controls!$B$8,"Medium","Normal"))
A7: P-006 | B7: Echo Service Transition | C7: Harbor Bank | D7: V. Shah | E7: PFA-02 | F7: BA-03 | G7: Active | H7: 690 | I7: 470 | J7: 350 | K7: 465 | L7: 390 | M7: 660 | N7: =IFERROR((L7-J7)/L7,0) | O7: =IFERROR((M7-K7)/M7,0) | P7: Service Acceptance | Q7: 46263 | R7: Missed | S7: 80 | T7: 46264 | U7: Overdue | V7: Transition Revenue | W7: 46263 | X7: Missed | Y7: 160 | Z7: 150 | AA7: 154 | AB7: Transition Pack | AC7: 46256 | AD7: Pending | AE7: 46263 | AF7: 46259 | AG7: =Q7-Controls!$B$2 | AH7: =IF(R7="Missed",3,IF(AND(R7="Upcoming",AG7<=Controls!$B$3),2,0)) | AI7: =IF(U7="Overdue",3,IF(U7="Due",2,IF(U7="Due Soon",1,0))) | AJ7: =IF(X7="Missed",3,IF(X7="Ready",2,0)) | AK7: =IF(OR(AA7>25,AA7>Y7*(1+Controls!$B$5)),2,IF(Z7<Y7,2,0)) | AL7: =IF(AND(AD7="Pending",Controls!$B$2-AC7>Controls!$B$4),2,IF(AD7="Pending",1,0)) | AM7: =IF(O7<15%,2,IF(O7<Controls!$B$6,1,0)) | AN7: =SUM(AH7:AM7) | AO7: =IF(AN7>=Controls!$B$7,"High",IF(AN7>=Controls!$B$8,"Medium","Normal"))
A8: P-007 | B8: Falcon CRM Transformation | C8: Evergreen Foods | D8: T. Das | E8: PFA-03 | F8: BA-04 | G8: Active | H8: 1120 | I8: 760 | J8: 585 | K8: 800 | L8: 610 | M8: 1080 | N8: =IFERROR((L8-J8)/L8,0) | O8: =IFERROR((M8-K8)/M8,0) | P8: Process Design | Q8: 46273 | R8: Upcoming | S8: 140 | T8: 46274 | U8: Not Due | V8: Design Revenue | W8: 46273 | X8: Pending | Y8: 280 | Z8: 225 | AA8: 275 | AB8: Process Design Pack | AC8: 46260 | AD8: Pending | AE8: 46275 | AF8: 46262 | AG8: =Q8-Controls!$B$2 | AH8: =IF(R8="Missed",3,IF(AND(R8="Upcoming",AG8<=Controls!$B$3),2,0)) | AI8: =IF(U8="Overdue",3,IF(U8="Due",2,IF(U8="Due Soon",1,0))) | AJ8: =IF(X8="Missed",3,IF(X8="Ready",2,0)) | AK8: =IF(OR(AA8>25,AA8>Y8*(1+Controls!$B$5)),2,IF(Z8<Y8,2,0)) | AL8: =IF(AND(AD8="Pending",Controls!$B$2-AC8>Controls!$B$4),2,IF(AD8="Pending",1,0)) | AM8: =IF(O8<15%,2,IF(O8<Controls!$B$6,1,0)) | AN8: =SUM(AH8:AM8) | AO8: =IF(AN8>=Controls!$B$7,"High",IF(AN8>=Controls!$B$8,"Medium","Normal"))
A9: P-008 | B9: Granite Finance Reporting | C9: Metro Utilities | D9: P. Bose | E9: PFA-03 | F9: BA-04 | G9: Active | H9: 540 | I9: 360 | J9: 300 | K9: 430 | L9: 390 | M9: 500 | N9: =IFERROR((L9-J9)/L9,0) | O9: =IFERROR((M9-K9)/M9,0) | P9: Monthly Reporting Sign-off | Q9: 46266 | R9: Missed | S9: 70 | T9: 46267 | U9: Due | V9: Reporting Revenue | W9: 46266 | X9: Ready | Y9: 90 | Z9: 70 | AA9: 105 | AB9: Reporting Pack | AC9: 46254 | AD9: Pending | AE9: 46264 | AF9: 46260 | AG9: =Q9-Controls!$B$2 | AH9: =IF(R9="Missed",3,IF(AND(R9="Upcoming",AG9<=Controls!$B$3),2,0)) | AI9: =IF(U9="Overdue",3,IF(U9="Due",2,IF(U9="Due Soon",1,0))) | AJ9: =IF(X9="Missed",3,IF(X9="Ready",2,0)) | AK9: =IF(OR(AA9>25,AA9>Y9*(1+Controls!$B$5)),2,IF(Z9<Y9,2,0)) | AL9: =IF(AND(AD9="Pending",Controls!$B$2-AC9>Controls!$B$4),2,IF(AD9="Pending",1,0)) | AM9: =IF(O9<15%,2,IF(O9<Controls!$B$6,1,0)) | AN9: =SUM(AH9:AM9) | AO9: =IF(AN9>=Controls!$B$7,"High",IF(AN9>=Controls!$B$8,"Medium","Normal"))
A10: P-009 | B10: Helix Workforce Portal | C10: Crown Health | D10: J. Roy | E10: PFA-03 | F10: BA-05 | G10: Active | H10: 870 | I10: 590 | J10: 420 | K10: 570 | L10: 470 | M10: 820 | N10: =IFERROR((L10-J10)/L10,0) | O10: =IFERROR((M10-K10)/M10,0) | P10: Business Readiness | Q10: 46285 | R10: Upcoming | S10: 120 | T10: 46287 | U10: Not Due | V10: Readiness Revenue | W10: 46285 | X10: Pending | Y10: 210 | Z10: 208 | AA10: 207 | AB10: Readiness Sign-off | AC10: 46265 | AD10: Pending | AE10: 46287 | AF10: 46265 | AG10: =Q10-Controls!$B$2 | AH10: =IF(R10="Missed",3,IF(AND(R10="Upcoming",AG10<=Controls!$B$3),2,0)) | AI10: =IF(U10="Overdue",3,IF(U10="Due",2,IF(U10="Due Soon",1,0))) | AJ10: =IF(X10="Missed",3,IF(X10="Ready",2,0)) | AK10: =IF(OR(AA10>25,AA10>Y10*(1+Controls!$B$5)),2,IF(Z10<Y10,2,0)) | AL10: =IF(AND(AD10="Pending",Controls!$B$2-AC10>Controls!$B$4),2,IF(AD10="Pending",1,0)) | AM10: =IF(O10<15%,2,IF(O10<Controls!$B$6,1,0)) | AN10: =SUM(AH10:AM10) | AO10: =IF(AN10>=Controls!$B$7,"High",IF(AN10>=Controls!$B$8,"Medium","Normal"))
A11: P-010 | B11: Ivory Procurement Redesign | C11: Nova Pharma | D11: D. Gupta | E11: PFA-04 | F11: BA-05 | G11: Active | H11: 930 | I11: 610 | J11: 455 | K11: 710 | L11: 500 | M11: 890 | N11: =IFERROR((L11-J11)/L11,0) | O11: =IFERROR((M11-K11)/M11,0) | P11: Design Approval | Q11: 46271 | R11: Upcoming | S11: 130 | T11: 46273 | U11: Due Soon | V11: Design Revenue | W11: 46271 | X11: Ready | Y11: 250 | Z11: 245 | AA11: 290 | AB11: Design Approval Pack | AC11: 46259 | AD11: Pending | AE11: 46271 | AF11: 46261 | AG11: =Q11-Controls!$B$2 | AH11: =IF(R11="Missed",3,IF(AND(R11="Upcoming",AG11<=Controls!$B$3),2,0)) | AI11: =IF(U11="Overdue",3,IF(U11="Due",2,IF(U11="Due Soon",1,0))) | AJ11: =IF(X11="Missed",3,IF(X11="Ready",2,0)) | AK11: =IF(OR(AA11>25,AA11>Y11*(1+Controls!$B$5)),2,IF(Z11<Y11,2,0)) | AL11: =IF(AND(AD11="Pending",Controls!$B$2-AC11>Controls!$B$4),2,IF(AD11="Pending",1,0)) | AM11: =IF(O11<15%,2,IF(O11<Controls!$B$6,1,0)) | AN11: =SUM(AH11:AM11) | AO11: =IF(AN11>=Controls!$B$7,"High",IF(AN11>=Controls!$B$8,"Medium","Normal"))
A12: P-011 | B12: Juniper Billing Transformation | C12: Silverline Media | D12: K. Paul | E12: PFA-04 | F12: BA-06 | G12: Active | H12: 1380 | I12: 900 | J12: 690 | K12: 920 | L12: 760 | M12: 1290 | N12: =IFERROR((L12-J12)/L12,0) | O12: =IFERROR((M12-K12)/M12,0) | P12: Billing UAT | Q12: 46279 | R12: Upcoming | S12: 190 | T12: 46280 | U12: Not Due | V12: UAT Revenue | W12: 46279 | X12: Pending | Y12: 360 | Z12: 355 | AA12: 350 | AB12: Billing UAT Sign-off | AC12: 46264 | AD12: Accepted | AE12: 46281 | AF12: 46264 | AG12: =Q12-Controls!$B$2 | AH12: =IF(R12="Missed",3,IF(AND(R12="Upcoming",AG12<=Controls!$B$3),2,0)) | AI12: =IF(U12="Overdue",3,IF(U12="Due",2,IF(U12="Due Soon",1,0))) | AJ12: =IF(X12="Missed",3,IF(X12="Ready",2,0)) | AK12: =IF(OR(AA12>25,AA12>Y12*(1+Controls!$B$5)),2,IF(Z12<Y12,2,0)) | AL12: =IF(AND(AD12="Pending",Controls!$B$2-AC12>Controls!$B$4),2,IF(AD12="Pending",1,0)) | AM12: =IF(O12<15%,2,IF(O12<Controls!$B$6,1,0)) | AN12: =SUM(AH12:AM12) | AO12: =IF(AN12>=Controls!$B$7,"High",IF(AN12>=Controls!$B$8,"Medium","Normal"))
A13: P-012 | B13: Keystone Contract Management | C13: Redwood Services | D13: G. Nair | E13: PFA-04 | F13: BA-06 | G13: Active | H13: 610 | I13: 420 | J13: 345 | K13: 470 | L13: 315 | M13: 585 | N13: =IFERROR((L13-J13)/L13,0) | O13: =IFERROR((M13-K13)/M13,0) | P13: Contract Approval | Q13: 46274 | R13: Upcoming | S13: 95 | T13: 46275 | U13: Not Due | V13: Contract Revenue | W13: 46274 | X13: Ready | Y13: 155 | Z13: 140 | AA13: 165 | AB13: Contract Sign-off | AC13: 46262 | AD13: Pending | AE13: 46277 | AF13: 46262 | AG13: =Q13-Controls!$B$2 | AH13: =IF(R13="Missed",3,IF(AND(R13="Upcoming",AG13<=Controls!$B$3),2,0)) | AI13: =IF(U13="Overdue",3,IF(U13="Due",2,IF(U13="Due Soon",1,0))) | AJ13: =IF(X13="Missed",3,IF(X13="Ready",2,0)) | AK13: =IF(OR(AA13>25,AA13>Y13*(1+Controls!$B$5)),2,IF(Z13<Y13,2,0)) | AL13: =IF(AND(AD13="Pending",Controls!$B$2-AC13>Controls!$B$4),2,IF(AD13="Pending",1,0)) | AM13: =IF(O13<15%,2,IF(O13<Controls!$B$6,1,0)) | AN13: =SUM(AH13:AM13) | AO13: =IF(AN13>=Controls!$B$7,"High",IF(AN13>=Controls!$B$8,"Medium","Normal"))
... A21: P-020 | B21: Summit Revenue Assurance | C21: Vantage Tech | D21: P. Singh | E21: PFA-07 | F21: BA-10 | G21: Active | H21: 1320 | I21: 860 | J21: 670 | K21: 970 | L21: 720 | M21: 1200 | N21: =IFERROR((L21-J21)/L21,0) | O21: =IFERROR((M21-K21)/M21,0) | P21: Revenue Validation | Q21: 46268 | R21: Upcoming | S21: 210 | T21: 46269 | U21: Due Soon | V21: Validation Revenue | W21: 46268 | X21: Ready | Y21: 340 | Z21: 320 | AA21: 345 | AB21: Validation Sign-off | AC21: 46263 | AD21: Pending | AE21: 46270 | AF21: 46263 | AG21: =Q21-Controls!$B$2 | AH21: =IF(R21="Missed",3,IF(AND(R21="Upcoming",AG21<=Controls!$B$3),2,0)) | AI21: =IF(U21="Overdue",3,IF(U21="Due",2,IF(U21="Due Soon",1,0))) | AJ21: =IF(X21="Missed",3,IF(X21="Ready",2,0)) | AK21: =IF(OR(AA21>25,AA21>Y21*(1+Controls!$B$5)),2,IF(Z21<Y21,2,0)) | AL21: =IF(AND(AD21="Pending",Controls!$B$2-AC21>Controls!$B$4),2,IF(AD21="Pending",1,0)) | AM21: =IF(O21<15%,2,IF(O21<Controls!$B$6,1,0)) | AN21: =SUM(AH21:AM21) | AO21: =IF(AN21>=Controls!$B$7,"High",IF(AN21>=Controls!$B$8,"Medium","Normal"))

Sheet Command Catalog
A1: No. | B1: Persona | C1: Natural-language command | D1: Expected answer intent | E1: Primary data domains | F1: Priority logic
A2: 1 | B2: Project Financial Analyst | C2: Which projects need my attention today? | D2: Rank portfolio exceptions by urgency and financial/operational impact | E2: Milestones, Billing, Revenue, Time, Acceptance, Margin | F2: High score first; explain evidence and next action
A3: 2 | B3: Project Financial Analyst / Business Analyst | C3: Which project milestones are due in the next 14 days? | D3: List upcoming milestones with dates and owners | E3: Milestones | F3: Due date within 14 days
A4: 3 | B4: Project Financial Analyst / Business Analyst | C4: Which milestones have been missed? | D4: List overdue milestones and days overdue | E4: Milestones | F4: Milestone status = Missed
A5: 4 | B5: Project Financial Analyst | C5: Which projects have invoicing due? | D5: Identify invoices due or overdue | E5: Billing | F5: Invoice status = Due / Overdue
A6: 5 | B6: Project Financial Analyst | C6: Which projects have revenue to be recognised? | D6: Identify revenue events ready for recognition | E6: Revenue | F6: Revenue status = Ready
A7: 6 | B7: Project Financial Analyst | C7: Which projects have potential missed revenue recognition? | D7: Identify expected revenue dates that have passed without recognition | E7: Revenue | F7: Revenue status = Missed
A8: 7 | B8: Project Financial Analyst | C8: Which projects have missing time entries? | D8: Identify projects where submitted hours are below planned expectations | E8: Time | F8: Submitted hours < planned hours
A9: 8 | B9: Project Financial Analyst / Business Analyst | C9: Which projects have excess time? | D9: Identify projects where actual hours materially exceed plan | E9: Time | F9: Actual hours > planned hours by threshold
A10: 9 | B10: Business Analyst | C10: Which projects are waiting for customer acceptance? | D10: List deliverables submitted but still awaiting customer response | E10: Customer Acceptance | F10: Pending acceptance beyond threshold
A11: 10 | B11: Project Financial Analyst | C11: Which projects show deteriorating financial health? | D11: Highlight margin or forecast deterioration | E11: Financial | F11: Low forecast margin and adverse forecast trend

Sheet Controls
A1: Control | B1: Value | C1: Purpose
A2: As of Date | B2: 46267 | C2: Prototype evaluation date
A3: Upcoming Milestone Window (days) | B3: 14 | C3: Questions about milestones approaching
A4: Customer Acceptance Threshold (days) | B4: 5 | C4: Days pending before priority increases
A5: Excess Time Threshold (%) | B5: 0.1 | C5: Actual hours above planned hours
A6: Low Forecast Margin Threshold (%) | B6: 0.2 | C6: Flags financial health attention
A7: High Attention Score | B7: 7 | C7: High-priority projects
A8: Medium Attention Score | B8: 4 | C8: Medium-priority projects
